{
  "name": "默认方案",
  "steps": [
    {
      "tool_type": "MultiROI",
      "params": {
        "regions": [
          {
            "name": "Label1",
            "x": 2000,
            "y": 601,
            "width": 400,
            "height": 750,
            "enabled": true
          },
          {
            "name": "Label2",
            "x": 988,
            "y": 576,
            "width": 356,
            "height": 717,
            "enabled": true
          },
          {
            "name": "Label3",
            "x": 80,
            "y": 500,
            "width": 400,
            "height": 800,
            "enabled": true
          },
          {
            "name": "Foot mat1",
            "x": 84,
            "y": 203,
            "width": 300,
            "height": 300,
            "enabled": true
          },
          {
            "name": "Foot mat2",
            "x": 2490,
            "y": 270,
            "width": 300,
            "height": 300,
            "enabled": true
          },
          {
            "name": "Foot mat3",
            "x": 2480,
            "y": 1420,
            "width": 230,
            "height": 230,
            "enabled": true
          },
          {
            "name": "Foot mat4",
            "x": 50,
            "y": 1250,
            "width": 400,
            "height": 400,
            "enabled": true
          },
          {
            "name": "区域8",
            "x": 1790,
            "y": 320,
            "width": 250,
            "height": 250,
            "enabled": true
          }
        ],
        "use_percentage": false,
        "input_source": "原始图像"
      },
      "enabled": true,
      "judge_rule": null
    },
    {
      "tool_type": "TemplateMatch",
      "params": {
        "mode": "standard",
        "method": "TM_CCOEFF_NORMED",
        "threshold": 0.7999999999999999,
        "template_path": "D:/Python project/VisionTest/model/deep/OK1.jpg",
        "template_data": null,
        "angle_start": -30,
        "angle_end": 30,
        "angle_step": 5,
        "feature_mode": "sift",
        "min_matches": 1,
        "nms_distance": 20,
        "use_mask": false,
        "mask_path": "",
        "_input_source": "region:Foot mat1"
      },
      "enabled": true,
      "judge_rule": null
    },
    {
      "tool_type": "TemplateMatch",
      "params": {
        "mode": "rotation",
        "method": "TM_CCOEFF_NORMED",
        "threshold": 0.8,
        "template_path": "D:/Python project/VisionTest/model/deep/OK2.jpg",
        "template_data": null,
        "angle_start": -30,
        "angle_end": 30,
        "angle_step": 5,
        "feature_mode": "sift",
        "min_matches": 10,
        "nms_distance": 20,
        "use_mask": false,
        "mask_path": "",
        "_input_source": "region:Foot mat2"
      },
      "enabled": true,
      "judge_rule": null
    },
    {
      "tool_type": "TemplateMatch",
      "params": {
        "mode": "standard",
        "method": "TM_CCOEFF_NORMED",
        "threshold": 0.8,
        "template_path": "D:/Python project/VisionTest/model/deep/OK3.jpg",
        "template_data": null,
        "angle_start": -30,
        "angle_end": 30,
        "angle_step": 5,
        "feature_mode": "sift",
        "min_matches": 10,
        "nms_distance": 20,
        "use_mask": false,
        "mask_path": "",
        "_input_source": "region:Foot mat3"
      },
      "enabled": true,
      "judge_rule": null
    },
    {
      "tool_type": "TemplateMatch",
      "params": {
        "mode": "standard",
        "method": "TM_CCOEFF_NORMED",
        "threshold": 0.8,
        "template_path": "D:/Python project/VisionTest/model/deep/OK4.jpg",
        "template_data": null,
        "angle_start": -30,
        "angle_end": 30,
        "angle_step": 5,
        "feature_mode": "sift",
        "min_matches": 10,
        "nms_distance": 20,
        "use_mask": false,
        "mask_path": "",
        "_input_source": "region:Foot mat4"
      },
      "enabled": true,
      "judge_rule": null
    },
    {
      "tool_type": "TemplateMatch",
      "params": {
        "mode": "standard",
        "method": "TM_CCOEFF_NORMED",
        "threshold": 0.8,
        "template_path": "D:/Python project/VisionTest/model/titile/OK1.jpg",
        "template_data": null,
        "angle_start": -30,
        "angle_end": 30,
        "angle_step": 5,
        "feature_mode": "sift",
        "min_matches": 10,
        "nms_distance": 20,
        "use_mask": false,
        "mask_path": "",
        "_input_source": "region:Label3"
      },
      "enabled": true,
      "judge_rule": null
    },
    {
      "tool_type": "TemplateMatch",
      "params": {
        "mode": "standard",
        "method": "TM_CCOEFF_NORMED",
        "threshold": 0.8,
        "template_path": "D:/Python project/VisionTest/model/titile/OK2.jpg",
        "template_data": null,
        "angle_start": -30,
        "angle_end": 30,
        "angle_step": 5,
        "feature_mode": "sift",
        "min_matches": 10,
        "nms_distance": 20,
        "use_mask": false,
        "mask_path": "",
        "_input_source": "region:Label2"
      },
      "enabled": true,
      "judge_rule": null
    },
    {
      "tool_type": "TemplateMatch",
      "params": {
        "mode": "rotation",
        "method": "TM_CCOEFF_NORMED",
        "threshold": 0.8,
        "template_path": "D:/Python project/VisionTest/model/titile/OK3.jpg",
        "template_data": null,
        "angle_start": -30,
        "angle_end": 30,
        "angle_step": 2.0,
        "feature_mode": "sift",
        "min_matches": 10,
        "nms_distance": 20,
        "use_mask": false,
        "mask_path": "",
        "_input_source": "region:Label1"
      },
      "enabled": true,
      "judge_rule": null
    },
    {
      "tool_type": "TemplateMatch",
      "params": {
        "mode": "standard",
        "method": "TM_CCOEFF_NORMED",
        "threshold": 0.8,
        "template_path": "D:/Python project/VisionTest/model/titile/OK4.jpg",
        "template_data": null,
        "angle_start": -30,
        "angle_end": 30,
        "angle_step": 5,
        "feature_mode": "sift",
        "min_matches": 10,
        "nms_distance": 20,
        "use_mask": false,
        "mask_path": ""
      },
      "enabled": true,
      "judge_rule": null
    }
  ]
}